dusted/__init__.py
dusted/__main__.py
dusted/assets/error.png
dusted/assets/warning.png
dusted/broadcaster.py
dusted/commands.py
dusted/config.py
dusted/cursor.py
dusted/diagnostics_summary_view.py
dusted/dialog.py
dusted/dustforce/__init__.py
dusted/dustforce/linux.py
dusted/dustforce/windows.py
dusted/geom/__init__.py
dusted/geom/tiles.py
dusted/gui.py
dusted/inputs.py
dusted/inputs_view.py
dusted/jump_to_frame.py
dusted/level.py
dusted/level_view.py
dusted/nexus_script.py
dusted/replay_diagnostics.py
dusted/replay_metadata.py
dusted/undo_stack.py
dusted/utils.py
dusted-1.8.0.dist-info/WHEEL
dusted-1.8.0.dist-info/entry_points.txt
dusted-1.8.0.dist-info/METADATA
dusted-1.8.0.dist-info/RECORD
