Metadata-Version: 2.4
Name: dusted
Version: 1.8.0
Summary: Dustforce replay editor
Author: Alex Morson
Author-email: Alex Morson <alexmorson@btinternet.com>
License-Expression: MIT
Classifier: License :: OSI Approved :: MIT License
Classifier: Programming Language :: Python :: 3
Requires-Dist: dustmaker>=1.2.0
Requires-Dist: platformdirs>=4.5.1
Requires-Dist: requests>=2.32.5
Requires-Python: >=3.10
Project-URL: Changelog, https://github.com/alexmorson/dusted/releases
Project-URL: Source, https://github.com/alexmorson/dusted
